django_admin_select_columns/__init__.py
django_admin_select_columns/apps.py
django_admin_select_columns/mixins.py
django_admin_select_columns/models.py
django_admin_select_columns/py.typed
django_admin_select_columns/migrations/0001_initial.py
django_admin_select_columns/migrations/__init__.py
django_admin_select_columns/templates/admin/change_list.html
django_admin_select_columns/templates/select_columns/select_columns.html
django_admin_select_columns-1.0.3.dist-info/licenses/LICENSE
django_admin_select_columns-1.0.3.dist-info/METADATA
django_admin_select_columns-1.0.3.dist-info/WHEEL
django_admin_select_columns-1.0.3.dist-info/top_level.txt
django_admin_select_columns-1.0.3.dist-info/RECORD
