Metadata-Version: 2.4
Name: django-admin-select-columns
Version: 1.0.3
Summary: Dynamically select columns in django admin changelist view with persistence
Author-email: Pradish Bijukchhe <pradish@sandbox.com.np>
License: Copyright (c) 2025 Pradish Bijukchhe
Project-URL: Homepage, https://github.com/sandbox-pokhara/django-admin-select-columns
Project-URL: Issues, https://github.com/sandbox-pokhara/django-admin-select-columns/issues
Classifier: Programming Language :: Python :: 3
Requires-Python: >=3.7
License-File: LICENSE
Requires-Dist: Django
Provides-Extra: pre-commit
Requires-Dist: pre-commit; extra == "pre-commit"
Requires-Dist: django-types; extra == "pre-commit"
Dynamic: license-file
